pyautoencoder/__init__.py
pyautoencoder/_version.py
pyautoencoder/_base/__init__.py
pyautoencoder/_base/base.py
pyautoencoder/experimental/__init__.py
pyautoencoder/experimental/hypernetworks.py
pyautoencoder/experimental/benchmark_datasets/__init__.py
pyautoencoder/experimental/benchmark_datasets/disentanglement.py
pyautoencoder/loss/__init__.py
pyautoencoder/loss/base.py
pyautoencoder/vanilla/__init__.py
pyautoencoder/vanilla/autoencoder.py
pyautoencoder/variational/__init__.py
pyautoencoder/variational/stochastic_layers.py
pyautoencoder/variational/vae.py
pyautoencoder-1.1.0.dist-info/licenses/LICENSE
pyautoencoder-1.1.0.dist-info/METADATA
pyautoencoder-1.1.0.dist-info/WHEEL
pyautoencoder-1.1.0.dist-info/top_level.txt
pyautoencoder-1.1.0.dist-info/RECORD
