Metadata-Version: 2.4
Name: pyautoencoder
Version: 1.1.0
Summary: A Python package offering implementations of state-of-the-art autoencoder architectures in PyTorch.
Author: Andrea Pollastro
License: MIT
Project-URL: Homepage, https://github.com/andrea-pollastro/pyautoencoder
Project-URL: Repository, https://github.com/andrea-pollastro/pyautoencoder
Keywords: autoencoder,pytorch,deep learning,machine learning,representation learning,dimensionality reduction,generative models
Classifier: Operating System :: OS Independent
Classifier: Intended Audience :: Science/Research
Classifier: Intended Audience :: Developers
Classifier: License :: OSI Approved :: MIT License
Classifier: Programming Language :: Python :: 3
Classifier: Programming Language :: Python :: 3 :: Only
Classifier: Programming Language :: Python :: 3.10
Classifier: Programming Language :: Python :: 3.11
Classifier: Programming Language :: Python :: 3.12
Classifier: Programming Language :: Python :: 3.13
Classifier: Programming Language :: Python :: 3.14
Classifier: Topic :: Scientific/Engineering :: Artificial Intelligence
Classifier: Topic :: Software Development :: Libraries :: Python Modules
Requires-Python: >=3.10
License-File: LICENSE
Requires-Dist: torch>=2.1.0
Dynamic: license-file
